colabcode/__init__.py
colabcode/code.py
colabcodeModbyBitGeek29-29.1.data/scripts/colabcode
colabcodeModbyBitGeek29-29.1.dist-info/LICENSE
colabcodeModbyBitGeek29-29.1.dist-info/METADATA
colabcodeModbyBitGeek29-29.1.dist-info/WHEEL
colabcodeModbyBitGeek29-29.1.dist-info/top_level.txt
colabcodeModbyBitGeek29-29.1.dist-info/RECORD
