Metadata-Version: 2.1
Name: colabcodeModbyBitGeek29
Version: 29.1
Summary: Mod version of ColabCode
Home-page: UNKNOWN
Author: Lufi Porndre
Author-email: porndrelufi@gmail.com
License: MIT License
Platform: linux
Platform: unix
Requires-Python: >3.5.2
License-File: LICENSE
Requires-Dist: pyngrok (>=5.0.0)
Requires-Dist: nest-asyncio (==1.4.3)
Requires-Dist: uvicorn (==0.13.1)
Requires-Dist: jupyterlab (==3.0.7)
